pybinanceapi/__init__.py
pybinanceapi/__main__.py
pybinanceapi/generated.py
pybinanceapi-0.1.3.dist-info/LICENSE
pybinanceapi-0.1.3.dist-info/METADATA
pybinanceapi-0.1.3.dist-info/WHEEL
pybinanceapi-0.1.3.dist-info/top_level.txt
pybinanceapi-0.1.3.dist-info/RECORD
