Metadata-Version: 2.1
Name: pybinanceapi
Version: 0.1.3
Summary: Python Wrapper for the Binance API
Home-page: https://github.com/nogira/py-binance-api
Author: nogira
License: MIT
Platform: UNKNOWN
